gpglib/__init__.py
gpglib/errors.py
gpglib/packet_parser.py
gpglib/structures.py
gpglib/utils.py
gpglib/version.py
gpglib/content_parsers/__init__.py
gpglib/content_parsers/base.py
gpglib/content_parsers/crypt.py
gpglib/content_parsers/data.py
gpglib/content_parsers/delegators.py
gpglib/content_parsers/keys.py
gpglib/content_parsers/session_keys.py
gpglib2-0.5.1.dist-info/METADATA
gpglib2-0.5.1.dist-info/WHEEL
gpglib2-0.5.1.dist-info/licenses/LICENSE
gpglib2-0.5.1.dist-info/RECORD
