Metadata-Version: 2.1
Name: gpglib2
Version: 0.5.1
Summary: A python3 compatible fork of gpglib, a Library for decrypting gpg that doesn't shell out to gpg
Author-email: Stephen Moore <stephen@delfick.com>
License-Expression: MIT
License-File: LICENSE
Keywords: decrypt,gpg
Requires-Python: >=3.8
Requires-Dist: bitstring==4.1.4
Requires-Dist: pycryptodome==3.19.1
Provides-Extra: tests
Requires-Dist: noseofyeti[black]==2.4.3; extra == 'tests'
Requires-Dist: pytest-helpers-namespace==2021.12.29; extra == 'tests'
Requires-Dist: pytest==7.4.3; extra == 'tests'
